{"chart_id":"t2_note_breakdown","chart_name":"二部笔记转化","source_url":"https://redbi.devops.xiaohongshu.com/analysis/edit?projectId=4&analysisId=53586624","dims":["AM四级部门(最新日期状态）"],"metrics":["商笔DGMV(求和)","新发商笔数(求和)","商笔曝光量(求和)","商笔阅读率（ctr）","商笔商品转化率","商笔GPM","商品笔记ces(求和)","商笔曝光量(求和)_周同比-变化率","商笔商品转化率_周同比-变化率","商笔阅读率（ctr）_周同比-变化率","商笔GPM_周同比-变化率","商品笔记ces(求和)_周同比-变化率","商笔DGMV(求和)_周同比-变化率","新发商笔数(求和)_周同比-变化率"],"filters":["日期 等于 2026-05-05~2026-05-11","AM四级部门(最新日期状态） 等于 五组（休食）"],"columns":["AM四级部门(最新日期状态）","商笔DGMV","新发商笔数","商笔曝光量","商笔阅读率（ctr）","商笔商品转化率","商笔GPM","商品笔记ces","商笔DGMV_环比-变化率","新发商笔数_环比-变化率","商笔曝光量_环比-变化率","商笔阅读率（ctr）_环比-变化率","商笔商品转化率_环比-变化率","商笔GPM_环比-变化率","商品笔记ces_环比-变化率"],"rows":[["五组（休食）",30062612.730000004,63859.0,844336855.0,0.17336890262832363,0.07288151565812899,35.60499882478777,3049977.0,1.1735361774595918,1.1544871794871794,1.0471168932442239,-0.06804322511214343,0.05856106450588243,0.06175479506449748,1.0431291059668528]],"total_rows":1,"rewrite_status":"rewritten","data_complete":true}